rdbl/__init__.py
rdbl/main.py
rdbl-0.1.5.dist-info/LICENSE.txt
rdbl-0.1.5.dist-info/METADATA
rdbl-0.1.5.dist-info/WHEEL
rdbl-0.1.5.dist-info/top_level.txt
rdbl-0.1.5.dist-info/RECORD
